{
  "name": "DeleteWorkspaceWithPolicy",
  "description": "Delete a workspace which contains a policy.",
  "serverSpecificationFile": "workspace-local.json",
  "kubernetes": {},
  "application": {},
  "testScripts": [
    {
      "name": "DeleteWorkspaceWithPolicy",
      "numberOfUserJourneyThreadsToRun": 1,
      "userJourneyThreadPoolSize": 1,
      "expectedTimeForEach": 5,
      "expectedTimeForEachUnit": "MINUTES",
      "parametersMap": {
        "spend-profile-id": "wm-default-spend-profile"
      }
    }
  ],
  "testUserFiles": ["bella.json"]
}
